[
  {
    "project_id": "P20230000",
    "client": "Renault",
    "industry": "Insurance",
    "is_repeat_client": false,
    "project_type": "AI/ML Deployment",
    "start_date": "2023-11-03",
    "end_date": "2024-10-28",
    "duration_months": 12,
    "sales_month": 11,
    "complexity": "Medium",
    "team_size": 10,
    "team_roles": [
      "Business Analyst",
      "Manager",
      "Data Scientist",
      "Project Manager",
      "Consultant",
      "Consultant",
      "Manager",
      "Cloud Architect",
      "Manager",
      "Manager"
    ],
    "revenue": 742066.57,
    "profit": 173991.14,
    "profit_margin": 0.23
  },
  {
    "project_id": "P20230001",
    "client": "AXA",
    "industry": "Transport",
    "is_repeat_client": false,
    "project_type": "Cloud Migration",
    "start_date": "2023-03-25",
    "end_date": "2023-09-21",
    "duration_months": 6,
    "sales_month": 3,
    "complexity": "High",
    "team_size": 9,
    "team_roles": [
      "Cloud Architect",
      "Manager",
      "Business Analyst",
      "Consultant",
      "Senior Consultant",
      "Senior Consultant",
      "Consultant",
      "Data Scientist",
      "Data Scientist"
    ],
    "revenue": 789900.89,
    "profit": 146513.39,
    "profit_margin": 0.19
  },
  {
    "project_id": "P20230002",
    "client": "Carrefour",
    "industry": "Transport",
    "is_repeat_client": false,
    "project_type": "Cybersecurity Audit",
    "start_date": "2023-04-03",
    "end_date": "2024-03-28",
    "duration_months": 12,
    "sales_month": 4,
    "complexity": "Low",
    "team_size": 4,
    "team_roles": [
      "Data Scientist",
      "Business Analyst",
      "Cloud Architect",
      "Senior Consultant"
    ],
    "revenue": 1042803.73,
    "profit": 267727.98,
    "profit_margin": 0.26
  },
  {
    "project_id": "P20230003",
    "client": "Airbus",
    "industry": "Pharma",
    "is_repeat_client": false,
    "project_type": "Digital Transformation",
    "start_date": "2023-11-03",
    "end_date": "2025-01-26",
    "duration_months": 15,
    "sales_month": 11,
    "complexity": "Low",
    "team_size": 5,
    "team_roles": [
      "Senior Consultant",
      "Business Analyst",
      "Senior Consultant",
      "Manager",
      "Manager"
    ],
    "revenue": 232302.07,
    "profit": 61427.83,
    "profit_margin": 0.26
  },
  {
    "project_id": "P20230004",
    "client": "BNP Paribas",
    "industry": "Retail",
    "is_repeat_client": false,
    "project_type": "Process Optimization",
    "start_date": "2023-05-26",
    "end_date": "2024-02-20",
    "duration_months": 9,
    "sales_month": 5,
    "complexity": "Low",
    "team_size": 9,
    "team_roles": [
      "Manager",
      "Data Scientist",
      "Business Analyst",
      "Cloud Architect",
      "Cloud Architect",
      "Manager",
      "Business Analyst",
      "Senior Consultant",
      "Project Manager"
    ],
    "revenue": 1479229.52,
    "profit": 474825.54,
    "profit_margin": 0.32
  },
  {
    "project_id": "P20230005",
    "client": "AXA",
    "industry": "Transport",
    "is_repeat_client": false,
    "project_type": "Digital Transformation",
    "start_date": "2023-02-26",
    "end_date": "2023-11-23",
    "duration_months": 9,
    "sales_month": 2,
    "complexity": "High",
    "team_size": 8,
    "team_roles": [
      "Business Analyst",
      "Project Manager",
      "Senior Consultant",
      "Manager",
      "Project Manager",
      "Business Analyst",
      "Senior Consultant",
      "Business Analyst"
    ],
    "revenue": 1317554.86,
    "profit": 387248.18,
    "profit_margin": 0.29
  },
  {
    "project_id": "P20230006",
    "client": "Carrefour",
    "industry": "Banking",
    "is_repeat_client": true,
    "project_type": "Data Analytics",
    "start_date": "2023-06-15",
    "end_date": "2024-06-09",
    "duration_months": 12,
    "sales_month": 6,
    "complexity": "High",
    "team_size": 5,
    "team_roles": [
      "Senior Consultant",
      "Data Scientist",
      "Manager",
      "Data Scientist",
      "Data Scientist"
    ],
    "revenue": 4456590.08,
    "profit": 941808.67,
    "profit_margin": 0.21,
    "_flagged": [
      "outlier_revenue"
    ]
  },
  {
    "project_id": "P20230007",
    "client": "AXA",
    "industry": "Telecom",
    "is_repeat_client": false,
    "project_type": "AI/ML Deployment",
    "start_date": "2023-04-19",
    "end_date": "2024-01-14",
    "duration_months": 9,
    "sales_month": 4,
    "complexity": "Low",
    "team_size": 12,
    "team_roles": [
      "Data Scientist",
      "Data Scientist",
      "Business Analyst",
      "Senior Consultant",
      "Senior Consultant",
      "Consultant",
      "Business Analyst",
      "Manager",
      "Business Analyst",
      "Data Scientist",
      "Project Manager",
      "Data Scientist"
    ],
    "revenue": 781011.6,
    "profit": 236088.74,
    "profit_margin": 0.3
  },
  {
    "project_id": "P20230008",
    "client": "Veolia",
    "industry": "Insurance",
    "is_repeat_client": false,
    "project_type": "Digital Transformation",
    "start_date": "2023-12-16",
    "end_date": "2024-12-10",
    "duration_months": 12,
    "sales_month": 12,
    "complexity": "Low",
    "team_size": 6,
    "team_roles": [
      "Business Analyst",
      "Consultant",
      "Project Manager",
      "Data Scientist",
      "Cloud Architect",
      "Manager"
    ],
    "revenue": 1010384.79,
    "profit": 232075.94,
    "profit_margin": 0.23
  },
  {
    "project_id": "P20230009",
    "client": "TotalEnergies",
    "industry": "Telecom",
    "is_repeat_client": false,
    "project_type": "Process Optimization",
    "start_date": "2023-03-25",
    "end_date": "2023-09-21",
    "duration_months": 6,
    "sales_month": 3,
    "complexity": "Medium",
    "team_size": 3,
    "team_roles": [
      "Manager",
      "Business Analyst",
      "Consultant"
    ],
    "revenue": 639307.31,
    "profit": 199562.47,
    "profit_margin": 0.31
  },
  {
    "project_id": "P20230010",
    "client": "SNCF",
    "industry": "Retail",
    "is_repeat_client": false,
    "project_type": "Data Analytics",
    "start_date": "2023-09-08",
    "end_date": "2023-12-07",
    "duration_months": 3,
    "sales_month": 9,
    "complexity": "Medium",
    "team_size": 11,
    "team_roles": [
      "Cloud Architect",
      "Business Analyst",
      "Senior Consultant",
      "Cloud Architect",
      "Cloud Architect",
      "Manager",
      "Consultant",
      "Consultant",
      "Project Manager",
      "Project Manager",
      "Data Scientist"
    ],
    "revenue": 1771362.74,
    "profit": 612024.05,
    "profit_margin": 0.35
  },
  {
    "project_id": "P20230011",
    "client": "TotalEnergies",
    "industry": "Retail",
    "is_repeat_client": false,
    "project_type": "Data Analytics",
    "start_date": "2023-11-28",
    "end_date": "2024-02-26",
    "duration_months": 3,
    "sales_month": 11,
    "complexity": "High",
    "team_size": 10,
    "team_roles": [
      "Consultant",
      "Consultant",
      "Consultant",
      "Manager",
      "Project Manager",
      "Senior Consultant",
      "Manager",
      "Data Scientist",
      "Business Analyst",
      "Cloud Architect"
    ],
    "revenue": 1017989.58,
    "profit": 227676.29,
    "profit_margin": 0.22
  },
  {
    "project_id": "P20230012",
    "client": "TotalEnergies",
    "industry": "Retail",
    "is_repeat_client": false,
    "project_type": "Data Analytics",
    "start_date": "2023-10-14",
    "end_date": "2024-01-12",
    "duration_months": 3,
    "sales_month": 10,
    "complexity": "Low",
    "team_size": 10,
    "team_roles": [
      "Business Analyst",
      "Senior Consultant",
      "Project Manager",
      "Senior Consultant",
      "Data Scientist",
      "Manager",
      "Data Scientist",
      "Cloud Architect",
      "Consultant",
      "Manager"
    ],
    "revenue": 1647154.14,
    "profit": 359127.4,
    "profit_margin": 0.22
  },
  {
    "project_id": "P20230013",
    "client": "L'Or\u00e9al",
    "industry": "Banking",
    "is_repeat_client": false,
    "project_type": "Data Analytics",
    "start_date": "2023-05-24",
    "end_date": "2024-05-18",
    "duration_months": 12,
    "sales_month": 5,
    "complexity": "High",
    "team_size": 3,
    "team_roles": [
      "Project Manager",
      "Consultant",
      "Senior Consultant"
    ],
    "revenue": 595755.63,
    "profit": 139083.78,
    "profit_margin": 0.23
  },
  {
    "project_id": "P20230014",
    "client": "Renault",
    "industry": "Pharma",
    "is_repeat_client": true,
    "project_type": "IT Outsourcing",
    "start_date": "2023-04-08",
    "end_date": "2023-10-05",
    "duration_months": 6,
    "sales_month": 4,
    "complexity": "Medium",
    "team_size": 6,
    "team_roles": [
      "Senior Consultant",
      "Senior Consultant",
      "Senior Consultant",
      "Business Analyst",
      "Business Analyst",
      "Data Scientist"
    ],
    "revenue": 719850.42,
    "profit": 160609.61,
    "profit_margin": 0.22
  },
  {
    "project_id": "P20230015",
    "client": "Sanofi",
    "industry": "Banking",
    "is_repeat_client": false,
    "project_type": "Digital Transformation",
    "start_date": "2023-02-09",
    "end_date": "2023-11-06",
    "duration_months": 9,
    "sales_month": 2,
    "complexity": "Low",
    "team_size": 12,
    "team_roles": [
      "Business Analyst",
      "Business Analyst",
      "Consultant",
      "Manager",
      "Data Scientist",
      "Manager",
      "Business Analyst",
      "Business Analyst",
      "Data Scientist",
      "Data Scientist",
      "Project Manager",
      "Consultant"
    ],
    "revenue": 1837116.97,
    "profit": 422139.88,
    "profit_margin": 0.23
  },
  {
    "project_id": "P20230016",
    "client": "Sanofi",
    "industry": "Pharma",
    "is_repeat_client": false,
    "project_type": "Process Optimization",
    "start_date": "2023-04-21",
    "end_date": "2024-01-16",
    "duration_months": 9,
    "sales_month": 4,
    "complexity": "Low",
    "team_size": 12,
    "team_roles": [
      "Project Manager",
      "Cloud Architect",
      "Business Analyst",
      "Project Manager",
      "Senior Consultant",
      "Project Manager",
      "Senior Consultant",
      "Cloud Architect",
      "Data Scientist",
      "Consultant",
      "Data Scientist",
      "Manager"
    ],
    "revenue": 407385.51,
    "profit": 116134.07,
    "profit_margin": 0.29
  },
  {
    "project_id": "P20230017",
    "client": "BNP Paribas",
    "industry": "Banking",
    "is_repeat_client": true,
    "project_type": "Digital Transformation",
    "start_date": "2023-12-11",
    "end_date": "2024-09-06",
    "duration_months": 9,
    "sales_month": 12,
    "complexity": "Low",
    "team_size": 11,
    "team_roles": [
      "Project Manager",
      "Consultant",
      "Business Analyst",
      "Business Analyst",
      "Business Analyst",
      "Cloud Architect",
      "Project Manager",
      "Senior Consultant",
      "Senior Consultant",
      "Project Manager",
      "Cloud Architect"
    ],
    "revenue": 1759927.47,
    "profit": 502253.85,
    "profit_margin": 0.29
  },
  {
    "project_id": "P20230018",
    "client": "Veolia",
    "industry": "Retail",
    "is_repeat_client": false,
    "project_type": "ERP Implementation",
    "start_date": "2023-03-17",
    "end_date": "2023-09-13",
    "duration_months": 6,
    "sales_month": 3,
    "complexity": "High",
    "team_size": 4,
    "team_roles": [
      "Senior Consultant",
      "Data Scientist",
      "Manager",
      "Senior Consultant"
    ],
    "revenue": 1669386.03,
    "profit": 278590.04,
    "profit_margin": 0.17
  },
  {
    "project_id": "P20230019",
    "client": "AXA",
    "industry": "Insurance",
    "is_repeat_client": false,
    "project_type": "Data Analytics",
    "start_date": "2023-07-07",
    "end_date": "2024-01-03",
    "duration_months": 6,
    "sales_month": 7,
    "complexity": "Low",
    "team_size": 10,
    "team_roles": [
      "Data Scientist",
      "Project Manager",
      "Data Scientist",
      "Business Analyst",
      "Senior Consultant",
      "Project Manager",
      "Manager",
      "Consultant",
      "Data Scientist",
      "Senior Consultant"
    ],
    "revenue": 1613170.6,
    "profit": 386437.09,
    "profit_margin": 0.24
  },
  {
    "project_id": "P20230020",
    "client": "BNP Paribas",
    "industry": "Energy",
    "is_repeat_client": true,
    "project_type": "Data Analytics",
    "start_date": "2023-11-08",
    "end_date": "2024-02-06",
    "duration_months": 3,
    "sales_month": 11,
    "complexity": "Low",
    "team_size": 8,
    "team_roles": [
      "Business Analyst",
      "Data Scientist",
      "Cloud Architect",
      "Manager",
      "Business Analyst",
      "Senior Consultant",
      "Business Analyst",
      "Data Scientist"
    ],
    "revenue": 882017.37,
    "profit": 276086.19,
    "profit_margin": 0.31
  },
  {
    "project_id": "P20230021",
    "client": "TotalEnergies",
    "industry": "Transport",
    "is_repeat_client": true,
    "project_type": "Process Optimization",
    "start_date": "2023-05-17",
    "end_date": "2023-11-13",
    "duration_months": 6,
    "sales_month": 5,
    "complexity": "Low",
    "team_size": 4,
    "team_roles": [
      "Senior Consultant",
      "Cloud Architect",
      "Data Scientist",
      "Business Analyst"
    ],
    "revenue": 1316039.85,
    "profit": 356974.32,
    "profit_margin": 0.27
  },
  {
    "project_id": "P20230022",
    "client": "Veolia",
    "industry": "Banking",
    "is_repeat_client": true,
    "project_type": "Digital Transformation",
    "start_date": "2023-10-02",
    "end_date": "2024-03-30",
    "duration_months": 6,
    "sales_month": 10,
    "complexity": "Medium",
    "team_size": 7,
    "team_roles": [
      "Manager",
      "Business Analyst",
      "Cloud Architect",
      "Data Scientist",
      "Senior Consultant",
      "Manager",
      "Data Scientist"
    ],
    "revenue": 2326590.93,
    "profit": 810605.21,
    "profit_margin": 0.35
  },
  {
    "project_id": "P20230023",
    "client": "Renault",
    "industry": "Public Sector",
    "is_repeat_client": true,
    "project_type": "Digital Transformation",
    "start_date": "2023-08-18",
    "end_date": "2024-05-14",
    "duration_months": 9,
    "sales_month": 8,
    "complexity": "High",
    "team_size": 10,
    "team_roles": [
      "Project Manager",
      "Manager",
      "Project Manager",
      "Project Manager",
      "Consultant",
      "Data Scientist",
      "Senior Consultant",
      "Senior Consultant",
      "Business Analyst",
      "Business Analyst"
    ],
    "revenue": 1977927.98,
    "profit": 549091.24,
    "profit_margin": 0.28
  },
  {
    "project_id": "P20230024",
    "client": "La Poste",
    "industry": "Telecom",
    "is_repeat_client": false,
    "project_type": "ERP Implementation",
    "start_date": "2023-04-24",
    "end_date": "2023-07-23",
    "duration_months": 3,
    "sales_month": 4,
    "complexity": "Low",
    "team_size": 7,
    "team_roles": [
      "Consultant",
      "Project Manager",
      "Senior Consultant",
      "Consultant",
      "Project Manager",
      "Business Analyst",
      "Business Analyst"
    ],
    "revenue": 1108427.0,
    "profit": 249070.15,
    "profit_margin": 0.22
  },
  {
    "project_id": "P20230025",
    "client": "Renault",
    "industry": "Telecom",
    "is_repeat_client": false,
    "project_type": "IT Outsourcing",
    "start_date": "2023-03-10",
    "end_date": "2024-03-04",
    "duration_months": 12,
    "sales_month": 3,
    "complexity": "Medium",
    "team_size": 6,
    "team_roles": [
      "Senior Consultant",
      "Business Analyst",
      "Manager",
      "Business Analyst",
      "Project Manager",
      "Project Manager"
    ],
    "revenue": 1641410.09,
    "profit": 324370.04,
    "profit_margin": 0.28
  },
  {
    "project_id": "P20230026",
    "client": "BNP Paribas",
    "industry": "Transport",
    "is_repeat_client": true,
    "project_type": "ERP Implementation",
    "start_date": "2023-02-07",
    "end_date": "2023-08-06",
    "duration_months": 6,
    "sales_month": 2,
    "complexity": "High",
    "team_size": 12,
    "team_roles": [
      "Business Analyst",
      "Cloud Architect",
      "Data Scientist",
      "Data Scientist",
      "Project Manager",
      "Business Analyst",
      "Senior Consultant",
      "Business Analyst",
      "Consultant",
      "Cloud Architect",
      "Business Analyst",
      "Senior Consultant"
    ],
    "revenue": 1101238.61,
    "profit": 208441.77,
    "profit_margin": 0.19
  },
  {
    "project_id": "P20230027",
    "client": "ENGIE",
    "industry": "Pharma",
    "is_repeat_client": false,
    "project_type": "Process Optimization",
    "start_date": "2023-01-10",
    "end_date": "2023-07-09",
    "duration_months": 6,
    "sales_month": 1,
    "complexity": "High",
    "team_size": 12,
    "team_roles": [
      "Project Manager",
      "Senior Consultant",
      "Business Analyst",
      "Cloud Architect",
      "Cloud Architect",
      "Consultant",
      "Manager",
      "Project Manager",
      "Business Analyst",
      "Manager",
      "Consultant",
      "Manager"
    ],
    "revenue": 307708.39,
    "profit": 81443.37,
    "profit_margin": 0.26
  },
  {
    "project_id": "P20230028",
    "client": "AXA",
    "industry": "Transport",
    "is_repeat_client": false,
    "project_type": "Cloud Migration",
    "start_date": "2023-05-10",
    "end_date": "2023-08-08",
    "duration_months": 3,
    "sales_month": 5,
    "complexity": "Low",
    "team_size": 8,
    "team_roles": [
      "Senior Consultant",
      "Project Manager",
      "Business Analyst",
      "Data Scientist",
      "Consultant",
      "Consultant",
      "Manager",
      "Senior Consultant"
    ],
    "revenue": 1468363.51,
    "profit": 328847.5,
    "profit_margin": 0.22
  },
  {
    "project_id": "P20230029",
    "client": "Soci\u00e9t\u00e9 G\u00e9n\u00e9rale",
    "industry": "Insurance",
    "is_repeat_client": false,
    "project_type": "Process Optimization",
    "start_date": "2023-03-06",
    "end_date": "2023-09-02",
    "duration_months": 6,
    "sales_month": 3,
    "complexity": "High",
    "team_size": 11,
    "team_roles": [
      "Manager",
      "Senior Consultant",
      "Data Scientist",
      "Senior Consultant",
      "Data Scientist",
      "Project Manager",
      "Business Analyst",
      "Consultant",
      "Business Analyst",
      "Manager",
      "Manager"
    ],
    "revenue": 1336558.79,
    "profit": 288062.28,
    "profit_margin": 0.22
  },
  {
    "project_id": "P20230030",
    "client": "EDF",
    "industry": "Telecom",
    "is_repeat_client": false,
    "project_type": "Cybersecurity Audit",
    "start_date": "2023-02-02",
    "end_date": "2024-01-28",
    "duration_months": 12,
    "sales_month": 2,
    "complexity": "Medium",
    "team_size": 7,
    "team_roles": [
      "Manager",
      "Senior Consultant",
      "Project Manager",
      "Business Analyst",
      "Consultant",
      "Cloud Architect",
      "Business Analyst"
    ],
    "revenue": 1829225.56,
    "profit": 595258.55,
    "profit_margin": 0.33
  },
  {
    "project_id": "P20230031",
    "client": "BNP Paribas",
    "industry": "Banking",
    "is_repeat_client": true,
    "project_type": "Digital Transformation",
    "start_date": "2023-07-25",
    "end_date": "2023-10-23",
    "duration_months": 3,
    "sales_month": 7,
    "complexity": "Medium",
    "team_size": 3,
    "team_roles": [
      "Business Analyst",
      "Project Manager",
      "Senior Consultant"
    ],
    "revenue": 905182.3,
    "profit": 242540.03,
    "profit_margin": 0.27
  },
  {
    "project_id": "P20230032",
    "client": "SNCF",
    "industry": "Insurance",
    "is_repeat_client": true,
    "project_type": "Data Analytics",
    "start_date": "2023-06-11",
    "end_date": "2024-03-07",
    "duration_months": 9,
    "sales_month": 6,
    "complexity": "Low",
    "team_size": 10,
    "team_roles": [
      "Manager",
      "Consultant",
      "Business Analyst",
      "Cloud Architect",
      "Business Analyst",
      "Cloud Architect",
      "Senior Consultant",
      "Project Manager",
      "Project Manager",
      "Cloud Architect"
    ],
    "revenue": 1687601.45,
    "profit": 436594.04,
    "profit_margin": 0.26
  },
  {
    "project_id": "P20230033",
    "client": "ENGIE",
    "industry": "Energy",
    "is_repeat_client": true,
    "project_type": "IT Outsourcing",
    "start_date": "2023-09-19",
    "end_date": "2024-09-13",
    "duration_months": 12,
    "sales_month": 9,
    "complexity": "Low",
    "team_size": 8,
    "team_roles": [
      "Cloud Architect",
      "Manager",
      "Project Manager",
      "Project Manager",
      "Consultant",
      "Business Analyst",
      "Project Manager",
      "Data Scientist"
    ],
    "revenue": 1943727.07,
    "profit": 389696.99,
    "profit_margin": 0.2
  },
  {
    "project_id": "P20230034",
    "client": "Airbus",
    "industry": "Banking",
    "is_repeat_client": true,
    "project_type": "Digital Transformation",
    "start_date": "2023-05-02",
    "end_date": "2024-01-27",
    "duration_months": 9,
    "sales_month": 5,
    "complexity": "Low",
    "team_size": 9,
    "team_roles": [
      "Data Scientist",
      "Senior Consultant",
      "Business Analyst",
      "Project Manager",
      "Senior Consultant",
      "Manager",
      "Data Scientist",
      "Manager",
      "Cloud Architect"
    ],
    "revenue": 1060831.59,
    "profit": 340654.33,
    "profit_margin": 0.32
  },
  {
    "project_id": "P20230035",
    "client": "SNCF",
    "industry": "Insurance",
    "is_repeat_client": true,
    "project_type": "ERP Implementation",
    "start_date": "2023-05-13",
    "end_date": "2023-11-09",
    "duration_months": 6,
    "sales_month": 5,
    "complexity": "Medium",
    "team_size": 9,
    "team_roles": [
      "Manager",
      "Business Analyst",
      "Business Analyst",
      "Consultant",
      "Data Scientist",
      "Cloud Architect",
      "Manager",
      "Cloud Architect",
      "Project Manager"
    ],
    "revenue": 1276776.27,
    "profit": 204991.43,
    "profit_margin": 0.23
  },
  {
    "project_id": "P20230036",
    "client": "Carrefour",
    "industry": "Telecom",
    "is_repeat_client": true,
    "project_type": "Cloud Migration",
    "start_date": "2023-10-01",
    "end_date": "2024-03-29",
    "duration_months": 6,
    "sales_month": 10,
    "complexity": "Low",
    "team_size": 12,
    "team_roles": [
      "Senior Consultant",
      "Senior Consultant",
      "Data Scientist",
      "Senior Consultant",
      "Cloud Architect",
      "Cloud Architect",
      "Data Scientist",
      "Project Manager",
      "Business Analyst",
      "Cloud Architect",
      "Data Scientist",
      "Data Scientist"
    ],
    "revenue": 1873803.1,
    "profit": 617112.64,
    "profit_margin": 0.33
  },
  {
    "project_id": "P20230037",
    "client": "AXA",
    "industry": "Pharma",
    "is_repeat_client": true,
    "project_type": "Digital Transformation",
    "start_date": "2023-03-27",
    "end_date": "2023-12-22",
    "duration_months": 9,
    "sales_month": 3,
    "complexity": "Low",
    "team_size": 3,
    "team_roles": [
      "Data Scientist",
      "Cloud Architect",
      "Data Scientist"
    ],
    "revenue": 1641614.45,
    "profit": 377063.86,
    "profit_margin": 0.33
  },
  {
    "project_id": "P20230038",
    "client": "Airbus",
    "industry": "Insurance",
    "is_repeat_client": true,
    "project_type": "Data Analytics",
    "start_date": "2023-11-09",
    "end_date": "2024-05-07",
    "duration_months": 6,
    "sales_month": 11,
    "complexity": "Low",
    "team_size": 5,
    "team_roles": [
      "Senior Consultant",
      "Project Manager",
      "Project Manager",
      "Business Analyst",
      "Manager"
    ],
    "revenue": 803048.36,
    "profit": 240811.75,
    "profit_margin": 0.3
  },
  {
    "project_id": "P20230039",
    "client": "Renault",
    "industry": "Public Sector",
    "is_repeat_client": false,
    "project_type": "AI/ML Deployment",
    "start_date": "2023-02-20",
    "end_date": "2023-11-17",
    "duration_months": 9,
    "sales_month": 2,
    "complexity": "Medium",
    "team_size": 11,
    "team_roles": [
      "Manager",
      "Consultant",
      "Project Manager",
      "Business Analyst",
      "Cloud Architect",
      "Manager",
      "Project Manager",
      "Manager",
      "Senior Consultant",
      "Project Manager",
      "Project Manager"
    ],
    "revenue": 934258.5,
    "profit": 262446.68,
    "profit_margin": 0.28
  },
  {
    "project_id": "P20230040",
    "client": "Carrefour",
    "industry": "Telecom",
    "is_repeat_client": true,
    "project_type": "ERP Implementation",
    "start_date": "2023-11-14",
    "end_date": "2024-08-10",
    "duration_months": 9,
    "sales_month": 11,
    "complexity": "Medium",
    "team_size": 4,
    "team_roles": [
      "Data Scientist",
      "Project Manager",
      "Data Scientist",
      "Manager"
    ],
    "revenue": 1827362.23,
    "profit": 558097.15,
    "profit_margin": 0.31
  },
  {
    "project_id": "P20230041",
    "client": "Soci\u00e9t\u00e9 G\u00e9n\u00e9rale",
    "industry": "Transport",
    "is_repeat_client": false,
    "project_type": "ERP Implementation",
    "start_date": "2023-05-10",
    "end_date": "2023-08-08",
    "duration_months": 3,
    "sales_month": 5,
    "complexity": "High",
    "team_size": 12,
    "team_roles": [
      "Senior Consultant",
      "Consultant",
      "Manager",
      "Senior Consultant",
      "Cloud Architect",
      "Data Scientist",
      "Cloud Architect",
      "Data Scientist",
      "Project Manager",
      "Manager",
      "Consultant",
      "Cloud Architect"
    ],
    "revenue": 1233389.42,
    "profit": 353048.3,
    "profit_margin": 0.29
  },
  {
    "project_id": "P20230042",
    "client": "EDF",
    "industry": "Banking",
    "is_repeat_client": false,
    "project_type": "Cloud Migration",
    "start_date": "2023-05-10",
    "end_date": "2023-11-06",
    "duration_months": 6,
    "sales_month": 5,
    "complexity": "Medium",
    "team_size": 9,
    "team_roles": [
      "Data Scientist",
      "Data Scientist",
      "Business Analyst",
      "Consultant",
      "Manager",
      "Cloud Architect",
      "Cloud Architect",
      "Senior Consultant",
      "Project Manager"
    ],
    "revenue": 635130.32,
    "profit": 120239.72,
    "profit_margin": 0.19
  },
  {
    "project_id": "P20230043",
    "client": "Renault",
    "industry": "Telecom",
    "is_repeat_client": true,
    "project_type": "IT Outsourcing",
    "start_date": "2023-09-08",
    "end_date": "2024-03-06",
    "duration_months": 6,
    "sales_month": 9,
    "complexity": "High",
    "team_size": 11,
    "team_roles": [
      "Manager",
      "Manager",
      "Manager",
      "Cloud Architect",
      "Manager",
      "Senior Consultant",
      "Business Analyst",
      "Consultant",
      "Business Analyst",
      "Business Analyst",
      "Project Manager"
    ],
    "revenue": 1752607.25,
    "profit": 476592.04,
    "profit_margin": 0.27
  },
  {
    "project_id": "P20230044",
    "client": "SNCF",
    "industry": "Telecom",
    "is_repeat_client": false,
    "project_type": "Cloud Migration",
    "start_date": "2023-12-27",
    "end_date": "2024-12-21",
    "duration_months": 12,
    "sales_month": 12,
    "complexity": "High",
    "team_size": 11,
    "team_roles": [
      "Business Analyst",
      "Data Scientist",
      "Business Analyst",
      "Data Scientist",
      "Cloud Architect",
      "Cloud Architect",
      "Manager",
      "Manager",
      "Business Analyst",
      "Consultant",
      "Manager"
    ],
    "revenue": 791173.88,
    "profit": 149121.7,
    "profit_margin": 0.19
  },
  {
    "project_id": "P20230045",
    "client": "Veolia",
    "industry": "Banking",
    "is_repeat_client": false,
    "project_type": "Digital Transformation",
    "start_date": "2023-06-14",
    "end_date": "2023-12-11",
    "duration_months": 6,
    "sales_month": 6,
    "complexity": "Medium",
    "team_size": 3,
    "team_roles": [
      "Data Scientist",
      "Data Scientist",
      "Project Manager"
    ],
    "revenue": 1185178.25,
    "profit": 280171.61,
    "profit_margin": 0.24
  },
  {
    "project_id": "P20230046",
    "client": "AXA",
    "industry": "Banking",
    "is_repeat_client": false,
    "project_type": "IT Outsourcing",
    "start_date": "2023-04-08",
    "end_date": "2023-07-07",
    "duration_months": 3,
    "sales_month": 4,
    "complexity": "Medium",
    "team_size": 7,
    "team_roles": [
      "Cloud Architect",
      "Consultant",
      "Manager",
      "Consultant",
      "Cloud Architect",
      "Project Manager",
      "Consultant"
    ],
    "revenue": 720603.97,
    "profit": 164043.36,
    "profit_margin": 0.23
  },
  {
    "project_id": "P20230047",
    "client": "BNP Paribas",
    "industry": "Banking",
    "is_repeat_client": true,
    "project_type": "Cybersecurity Audit",
    "start_date": "2023-05-12",
    "end_date": "2023-11-08",
    "duration_months": 6,
    "sales_month": 5,
    "complexity": "High",
    "team_size": 6,
    "team_roles": [
      "Project Manager",
      "Business Analyst",
      "Senior Consultant",
      "Manager",
      "Senior Consultant",
      "Manager"
    ],
    "revenue": 1206647.29,
    "profit": 349181.28,
    "profit_margin": 0.29
  },
  {
    "project_id": "P20230048",
    "client": "Carrefour",
    "industry": "Banking",
    "is_repeat_client": false,
    "project_type": "AI/ML Deployment",
    "start_date": "2023-11-13",
    "end_date": "2024-08-09",
    "duration_months": 9,
    "sales_month": 11,
    "complexity": "Medium",
    "team_size": 9,
    "team_roles": [
      "Cloud Architect",
      "Data Scientist",
      "Business Analyst",
      "Manager",
      "Consultant",
      "Manager",
      "Consultant",
      "Cloud Architect",
      "Data Scientist"
    ],
    "revenue": 1133354.77,
    "profit": 220172.7,
    "profit_margin": 0.19
  },
  {
    "project_id": "P20230049",
    "client": "L'Or\u00e9al",
    "industry": "Public Sector",
    "is_repeat_client": false,
    "project_type": "Data Analytics",
    "start_date": "2023-05-27",
    "end_date": "2023-11-23",
    "duration_months": 6,
    "sales_month": 5,
    "complexity": "Medium",
    "team_size": 7,
    "team_roles": [
      "Business Analyst",
      "Project Manager",
      "Manager",
      "Business Analyst",
      "Manager",
      "Data Scientist",
      "Cloud Architect"
    ],
    "revenue": 962988.6,
    "profit": 243440.22,
    "profit_margin": 0.25
  },
  {
    "project_id": "P20230050",
    "client": "L'Or\u00e9al",
    "industry": "Transport",
    "is_repeat_client": false,
    "project_type": "Digital Transformation",
    "start_date": "2023-11-11",
    "end_date": "2024-02-09",
    "duration_months": 3,
    "sales_month": 11,
    "complexity": "Medium",
    "team_size": 4,
    "team_roles": [
      "Data Scientist",
      "Project Manager",
      "Cloud Architect",
      "Consultant"
    ],
    "revenue": 1082196.75,
    "profit": 222695.43,
    "profit_margin": 0.29
  },
  {
    "project_id": "P20230051",
    "client": "SNCF",
    "industry": "Insurance",
    "is_repeat_client": false,
    "project_type": "Process Optimization",
    "start_date": "2023-01-05",
    "end_date": "2023-04-05",
    "duration_months": 3,
    "sales_month": 1,
    "complexity": "Medium",
    "team_size": 8,
    "team_roles": [
      "Business Analyst",
      "Consultant",
      "Senior Consultant",
      "Manager",
      "Senior Consultant",
      "Manager",
      "Project Manager",
      "Data Scientist"
    ],
    "revenue": 435742.35,
    "profit": 101583.83,
    "profit_margin": 0.23
  },
  {
    "project_id": "P20230052",
    "client": "BNP Paribas",
    "industry": "Banking",
    "is_repeat_client": true,
    "project_type": "Cloud Migration",
    "start_date": "2023-09-20",
    "end_date": "2023-12-19",
    "duration_months": 3,
    "sales_month": 9,
    "complexity": "Low",
    "team_size": 12,
    "team_roles": [
      "Senior Consultant",
      "Manager",
      "Business Analyst",
      "Data Scientist",
      "Manager",
      "Data Scientist",
      "Manager",
      "Data Scientist",
      "Senior Consultant",
      "Senior Consultant",
      "Cloud Architect",
      "Data Scientist"
    ],
    "revenue": 6028148.67,
    "profit": 1356893.08,
    "profit_margin": 0.23,
    "_flagged": [
      "outlier_revenue",
      "outlier_profit"
    ]
  },
  {
    "project_id": "P20230053",
    "client": "Soci\u00e9t\u00e9 G\u00e9n\u00e9rale",
    "industry": "Public Sector",
    "is_repeat_client": false,
    "project_type": "Process Optimization",
    "start_date": "2023-02-14",
    "end_date": "2023-08-13",
    "duration_months": 6,
    "sales_month": 2,
    "complexity": "High",
    "team_size": 11,
    "team_roles": [
      "Project Manager",
      "Business Analyst",
      "Senior Consultant",
      "Business Analyst",
      "Business Analyst",
      "Manager",
      "Manager",
      "Project Manager",
      "Project Manager",
      "Business Analyst",
      "Consultant"
    ],
    "revenue": 386224.15,
    "profit": 74323.95,
    "profit_margin": 0.19
  },
  {
    "project_id": "P20230054",
    "client": "SNCF",
    "industry": "Telecom",
    "is_repeat_client": false,
    "project_type": "Cloud Migration",
    "start_date": "2023-05-15",
    "end_date": "2023-08-13",
    "duration_months": 3,
    "sales_month": 5,
    "complexity": "High",
    "team_size": 7,
    "team_roles": [
      "Project Manager",
      "Data Scientist",
      "Consultant",
      "Data Scientist",
      "Senior Consultant",
      "Senior Consultant",
      "Senior Consultant"
    ],
    "revenue": 1083153.25,
    "profit": 205163.39,
    "profit_margin": 0.19
  },
  {
    "project_id": "P20230055",
    "client": "AXA",
    "industry": "Transport",
    "is_repeat_client": true,
    "project_type": "ERP Implementation",
    "start_date": "2023-04-28",
    "end_date": "2023-10-25",
    "duration_months": 6,
    "sales_month": 4,
    "complexity": "Low",
    "team_size": 10,
    "team_roles": [
      "Consultant",
      "Project Manager",
      "Consultant",
      "Project Manager",
      "Senior Consultant",
      "Manager",
      "Business Analyst",
      "Manager",
      "Project Manager",
      "Cloud Architect"
    ],
    "revenue": 1402893.63,
    "profit": 485694.97,
    "profit_margin": 0.35
  },
  {
    "project_id": "P20230056",
    "client": "TotalEnergies",
    "industry": "Energy",
    "is_repeat_client": false,
    "project_type": "Digital Transformation",
    "start_date": "2023-10-28",
    "end_date": "2024-07-24",
    "duration_months": 9,
    "sales_month": 10,
    "complexity": "Low",
    "team_size": 8,
    "team_roles": [
      "Cloud Architect",
      "Data Scientist",
      "Manager",
      "Consultant",
      "Data Scientist",
      "Consultant",
      "Manager",
      "Business Analyst"
    ],
    "revenue": 2087328.59,
    "profit": 381378.17,
    "profit_margin": 0.26
  },
  {
    "project_id": "P20230057",
    "client": "Orange",
    "industry": "Public Sector",
    "is_repeat_client": false,
    "project_type": "IT Outsourcing",
    "start_date": "2023-10-23",
    "end_date": "2024-04-20",
    "duration_months": 6,
    "sales_month": 10,
    "complexity": "Medium",
    "team_size": 10,
    "team_roles": [
      "Business Analyst",
      "Project Manager",
      "Project Manager",
      "Cloud Architect",
      "Cloud Architect",
      "Data Scientist",
      "Senior Consultant",
      "Cloud Architect",
      "Data Scientist",
      "Cloud Architect"
    ],
    "revenue": 183318.21,
    "profit": 63864.5,
    "profit_margin": 0.35
  },
  {
    "project_id": "P20230058",
    "client": "Orange",
    "industry": "Transport",
    "is_repeat_client": false,
    "project_type": "Process Optimization",
    "start_date": "2023-10-01",
    "end_date": "2024-06-27",
    "duration_months": 9,
    "sales_month": 10,
    "complexity": "Medium",
    "team_size": 8,
    "team_roles": [
      "Senior Consultant",
      "Business Analyst",
      "Data Scientist",
      "Consultant",
      "Project Manager",
      "Project Manager",
      "Project Manager",
      "Manager"
    ],
    "revenue": 100054.69,
    "profit": 27265.71,
    "profit_margin": 0.27
  },
  {
    "project_id": "P20230059",
    "client": "Renault",
    "industry": "Retail",
    "is_repeat_client": false,
    "project_type": "Process Optimization",
    "start_date": "2023-01-25",
    "end_date": "2023-07-24",
    "duration_months": 6,
    "sales_month": 1,
    "complexity": "Medium",
    "team_size": 4,
    "team_roles": [
      "Business Analyst",
      "Cloud Architect",
      "Cloud Architect",
      "Senior Consultant"
    ],
    "revenue": 1479564.39,
    "profit": 477125.75,
    "profit_margin": 0.32
  }
]